LICENSE
MANIFEST.in
README.md
setup.cfg
setup.py
polynomial/__init__.py
polynomial/polynomial.py
polynomial.egg-info/PKG-INFO
polynomial.egg-info/SOURCES.txt
polynomial.egg-info/dependency_links.txt
polynomial.egg-info/top_level.txt