Metadata-Version: 2.1
Name: polynomial
Version: 0.21
Summary: This is a professional polynomial calculator and analyzer python module.
Home-page: https://github.com/Rainbow-Dreamer/polynomial
Author: Rainbow-Dreamer
Author-email: 1036889495@qq.com
License: LGPLv2.1
Download-URL: https://github.com/Rainbow-Dreamer/polynomial/archive/0.21.tar.gz
Keywords: polynomial,mathematics,statistics
Platform: UNKNOWN
Classifier: Development Status :: 3 - Alpha
Classifier: Intended Audience :: Developers
Classifier: Topic :: Software Development :: Build Tools
Classifier: License :: OSI Approved :: GNU Lesser General Public License v2 or later (LGPLv2+)
Classifier: Programming Language :: Python :: 3.6
Classifier: Programming Language :: Python :: 3.7
Classifier: Programming Language :: Python :: 3.8
Classifier: Programming Language :: Python :: 3.9
Classifier: Programming Language :: Python :: 3.10
License-File: LICENSE
